bhashini_client/__init__.py
bhashini_client/config.py
bhashini_client/core.py
bhashini_client/services/__init__.py
bhashini_client/services/asr_service.py
bhashini_client/services/nmt_service.py
bhashini_client/services/tts_service.py
bhashini_client/utils/__init__.py
bhashini_client/utils/request_handler.py
bhashini_client-0.1.5.dist-info/licenses/LICENSE
bhashini_client-0.1.5.dist-info/METADATA
bhashini_client-0.1.5.dist-info/WHEEL
bhashini_client-0.1.5.dist-info/top_level.txt
bhashini_client-0.1.5.dist-info/RECORD
