Metadata-Version: 2.4
Name: bhashini-client
Version: 0.1.5
Summary: A Python client for interacting with Bhashini inference services (ASR, NMT, TTS).
Home-page: https://github.com/your-org/bhashini-client
Author: Sai
Author-email: digitalindiabhashinidivision@gmail.com
Classifier: Programming Language :: Python :: 3
Classifier: License :: OSI Approved :: MIT License
Classifier: Operating System :: OS Independent
Requires-Python: >=3.8
License-File: LICENSE
Requires-Dist: requests>=2.25.0
Dynamic: author
Dynamic: author-email
Dynamic: classifier
Dynamic: description
Dynamic: description-content-type
Dynamic: home-page
Dynamic: license-file
Dynamic: requires-dist
Dynamic: requires-python
Dynamic: summary
